cc/__init__.py
cc/command.py
cc/constant.py
cc/register.py
cc/status.py
stspin/__init__.py
stspin/spin_chain.py
stspin/spin_device.py
stspin/utility.py
stspin/constants/__init__.py
stspin/constants/command.py
stspin/constants/constant.py
stspin/constants/register.py
stspin/constants/status.py
st_spin-0.0.22.4.dist-info/METADATA
st_spin-0.0.22.4.dist-info/WHEEL
st_spin-0.0.22.4.dist-info/top_level.txt
st_spin-0.0.22.4.dist-info/RECORD
