Metadata-Version: 2.1
Name: st-spin
Version: 0.0.22.4
Summary: Interface for ST SpinFamily motor drivers
Home-page: https://github.com/m-laniakea/st_spin
Author: eir
Author-email: m-laniakea@users.noreply.github.com
License: GPLv1
Platform: UNKNOWN
Requires-Dist: typing-extensions
Provides-Extra: spidev
Requires-Dist: spidev (==3.4) ; extra == 'spidev'
